<?xml version="1.0" encoding="UTF-8" ?>
<!DOCTYPE mapper PUBLIC "-//mybatis.org//DTD Mapper 3.0//EN" "http://mybatis.org/dtd/mybatis-3-mapper.dtd" >
<mapper namespace="top.testcross.zuji.mapper.PamLikeMapper" >
  <resultMap id="BaseResultMap" type="top.testcross.zuji.bean.PamLike" >
    
    <!-- 点赞id -->
    <id column="like_id" property="likeId" jdbcType="CHAR" />
    
    <!-- 用户id -->
    <result column="user_id" property="userId" jdbcType="CHAR" />
    
    <!-- 动态id -->
    <result column="post_id" property="postId" jdbcType="CHAR" />
    
    <!-- 点赞时间 -->
    <result column="like_create_time" property="likeCreateTime" jdbcType="TIMESTAMP" />
  </resultMap>
  <sql id="Example_Where_Clause" >
    <!--
      WARNING - @mbggenerated
      This element is automatically generated by MyBatis Generator, do not modify.
      This element was generated on Sun Nov 15 12:07:48 GMT+08:00 2020.
    -->
    <where >
      <foreach collection="oredCriteria" item="criteria" separator="or" >
        <if test="criteria.valid" >
          <trim prefix="(" suffix=")" prefixOverrides="and" >
            <foreach collection="criteria.criteria" item="criterion" >
              <choose >
                <when test="criterion.noValue" >
                  and ${criterion.condition}
                </when>
                <when test="criterion.singleValue" >
                  and ${criterion.condition} #{criterion.value}
                </when>
                <when test="criterion.betweenValue" >
                  and ${criterion.condition} #{criterion.value} and #{criterion.secondValue}
                </when>
                <when test="criterion.listValue" >
                  and ${criterion.condition}
                  <foreach collection="criterion.value" item="listItem" open="(" close=")" separator="," >
                    #{listItem}
                  </foreach>
                </when>
              </choose>
            </foreach>
          </trim>
        </if>
      </foreach>
    </where>
  </sql>
  <sql id="Update_By_Example_Where_Clause" >
    <!--
      WARNING - @mbggenerated
      This element is automatically generated by MyBatis Generator, do not modify.
      This element was generated on Sun Nov 15 12:07:48 GMT+08:00 2020.
    -->
    <where >
      <foreach collection="example.oredCriteria" item="criteria" separator="or" >
        <if test="criteria.valid" >
          <trim prefix="(" suffix=")" prefixOverrides="and" >
            <foreach collection="criteria.criteria" item="criterion" >
              <choose >
                <when test="criterion.noValue" >
                  and ${criterion.condition}
                </when>
                <when test="criterion.singleValue" >
                  and ${criterion.condition} #{criterion.value}
                </when>
                <when test="criterion.betweenValue" >
                  and ${criterion.condition} #{criterion.value} and #{criterion.secondValue}
                </when>
                <when test="criterion.listValue" >
                  and ${criterion.condition}
                  <foreach collection="criterion.value" item="listItem" open="(" close=")" separator="," >
                    #{listItem}
                  </foreach>
                </when>
              </choose>
            </foreach>
          </trim>
        </if>
      </foreach>
    </where>
  </sql>
  <sql id="Base_Column_List" >
    <!--
      WARNING - @mbggenerated
      This element is automatically generated by MyBatis Generator, do not modify.
      This element was generated on Sun Nov 15 12:07:48 GMT+08:00 2020.
    -->
    like_id, user_id, post_id, like_create_time
  </sql>
  <select id="selectByExample" resultMap="BaseResultMap" parameterType="top.testcross.zuji.bean.PamLikeExample" >
    <!--
      WARNING - @mbggenerated
      This element is automatically generated by MyBatis Generator, do not modify.
      This element was generated on Sun Nov 15 12:07:48 GMT+08:00 2020.
    -->
    select
    <if test="distinct" >
      distinct
    </if>
    <include refid="Base_Column_List" />
    from pam_like
    <if test="_parameter != null" >
      <include refid="Example_Where_Clause" />
    </if>
    <if test="orderByClause != null" >
      order by ${orderByClause}
    </if>
  </select>
  <select id="selectByPrimaryKey" resultMap="BaseResultMap" parameterType="java.lang.String" >
    <!--
      WARNING - @mbggenerated
      This element is automatically generated by MyBatis Generator, do not modify.
      This element was generated on Sun Nov 15 12:07:48 GMT+08:00 2020.
    -->
    select 
    <include refid="Base_Column_List" />
    from pam_like
    where like_id = #{likeId,jdbcType=CHAR}
  </select>
  <delete id="deleteByPrimaryKey" parameterType="java.lang.String" >
    <!--
      WARNING - @mbggenerated
      This element is automatically generated by MyBatis Generator, do not modify.
      This element was generated on Sun Nov 15 12:07:48 GMT+08:00 2020.
    -->
    delete from pam_like
    where like_id = #{likeId,jdbcType=CHAR}
  </delete>
  <delete id="deleteByExample" parameterType="top.testcross.zuji.bean.PamLikeExample" >
    <!--
      WARNING - @mbggenerated
      This element is automatically generated by MyBatis Generator, do not modify.
      This element was generated on Sun Nov 15 12:07:48 GMT+08:00 2020.
    -->
    delete from pam_like
    <if test="_parameter != null" >
      <include refid="Example_Where_Clause" />
    </if>
  </delete>
  <insert id="insert" >
    <!--
      WARNING - @mbggenerated
      This element is automatically generated by MyBatis Generator, do not modify.
      This element was generated on Sun Nov 15 12:07:48 GMT+08:00 2020.
    -->
    insert into pam_like (like_id, user_id, post_id, 
      like_create_time)
    values (#{likeId,jdbcType=CHAR}, #{userId,jdbcType=CHAR}, #{postId,jdbcType=CHAR}, 
      #{likeCreateTime,jdbcType=TIMESTAMP})
  </insert>
  <insert id="insertSelective" >
    <!--
      WARNING - @mbggenerated
      This element is automatically generated by MyBatis Generator, do not modify.
      This element was generated on Sun Nov 15 12:07:48 GMT+08:00 2020.
    -->
    insert into pam_like
    <trim prefix="(" suffix=")" suffixOverrides="," >
      <if test="likeId != null" >
        like_id,
      </if>
      <if test="userId != null" >
        user_id,
      </if>
      <if test="postId != null" >
        post_id,
      </if>
      <if test="likeCreateTime != null" >
        like_create_time,
      </if>
    </trim>
    <trim prefix="values (" suffix=")" suffixOverrides="," >
      <if test="likeId != null" >
        #{likeId,jdbcType=CHAR},
      </if>
      <if test="userId != null" >
        #{userId,jdbcType=CHAR},
      </if>
      <if test="postId != null" >
        #{postId,jdbcType=CHAR},
      </if>
      <if test="likeCreateTime != null" >
        #{likeCreateTime,jdbcType=TIMESTAMP},
      </if>
    </trim>
  </insert>
  <select id="countByExample" parameterType="top.testcross.zuji.bean.PamLikeExample" resultType="java.lang.Integer" >
    <!--
      WARNING - @mbggenerated
      This element is automatically generated by MyBatis Generator, do not modify.
      This element was generated on Sun Nov 15 12:07:48 GMT+08:00 2020.
    -->
    select count(*) from pam_like
    <if test="_parameter != null" >
      <include refid="Example_Where_Clause" />
    </if>
  </select>
  <update id="updateByExampleSelective" parameterType="map" >
    <!--
      WARNING - @mbggenerated
      This element is automatically generated by MyBatis Generator, do not modify.
      This element was generated on Sun Nov 15 12:07:48 GMT+08:00 2020.
    -->
    update pam_like
    <set >
      <if test="record.likeId != null" >
        like_id = #{record.likeId,jdbcType=CHAR},
      </if>
      <if test="record.userId != null" >
        user_id = #{record.userId,jdbcType=CHAR},
      </if>
      <if test="record.postId != null" >
        post_id = #{record.postId,jdbcType=CHAR},
      </if>
      <if test="record.likeCreateTime != null" >
        like_create_time = #{record.likeCreateTime,jdbcType=TIMESTAMP},
      </if>
    </set>
    <if test="_parameter != null" >
      <include refid="Update_By_Example_Where_Clause" />
    </if>
  </update>
  <update id="updateByExample" parameterType="map" >
    <!--
      WARNING - @mbggenerated
      This element is automatically generated by MyBatis Generator, do not modify.
      This element was generated on Sun Nov 15 12:07:48 GMT+08:00 2020.
    -->
    update pam_like
    set like_id = #{record.likeId,jdbcType=CHAR},
      user_id = #{record.userId,jdbcType=CHAR},
      post_id = #{record.postId,jdbcType=CHAR},
      like_create_time = #{record.likeCreateTime,jdbcType=TIMESTAMP}
    <if test="_parameter != null" >
      <include refid="Update_By_Example_Where_Clause" />
    </if>
  </update>
  <update id="updateByPrimaryKeySelective" >
    <!--
      WARNING - @mbggenerated
      This element is automatically generated by MyBatis Generator, do not modify.
      This element was generated on Sun Nov 15 12:07:48 GMT+08:00 2020.
    -->
    update pam_like
    <set >
      <if test="userId != null" >
        user_id = #{userId,jdbcType=CHAR},
      </if>
      <if test="postId != null" >
        post_id = #{postId,jdbcType=CHAR},
      </if>
      <if test="likeCreateTime != null" >
        like_create_time = #{likeCreateTime,jdbcType=TIMESTAMP},
      </if>
    </set>
    where like_id = #{likeId,jdbcType=CHAR}
  </update>
  <update id="updateByPrimaryKey" >
    <!--
      WARNING - @mbggenerated
      This element is automatically generated by MyBatis Generator, do not modify.
      This element was generated on Sun Nov 15 12:07:48 GMT+08:00 2020.
    -->
    update pam_like
    set user_id = #{userId,jdbcType=CHAR},
      post_id = #{postId,jdbcType=CHAR},
      like_create_time = #{likeCreateTime,jdbcType=TIMESTAMP}
    where like_id = #{likeId,jdbcType=CHAR}
  </update>
  
  <!-- Generate time: 2020-11-15 12:07:48 ### -->


  <!-- Your codes goes here!!! -->
  
</mapper>